stdoutmonitor
